src/__init__.py
src/cli.py
src/client.py
src/core.py
src/parser.py
src/slack_client.py
snap_notify-0.2.1.dist-info/LICENSE
snap_notify-0.2.1.dist-info/METADATA
snap_notify-0.2.1.dist-info/WHEEL
snap_notify-0.2.1.dist-info/entry_points.txt
snap_notify-0.2.1.dist-info/RECORD
