Metadata-Version: 2.3
Name: snap-notify
Version: 0.2.1
Summary: 
License: MIT
Author: cdaviis
Author-email: chrisdavis179@gmail.com
Requires-Python: >=3.12,<3.13
Classifier: License :: OSI Approved :: MIT License
Classifier: Programming Language :: Python :: 3
Classifier: Programming Language :: Python :: 3.12
Requires-Dist: click (>=8.1.8,<9.0.0)
Requires-Dist: httpcore (>=1.0.7)
Requires-Dist: python-dotenv (>=1.0.0,<2.0.0)
Requires-Dist: slack-sdk (>=3.35.0,<4.0.0)
Requires-Dist: urllib3 (>=2.3.0)
